boxx/__init__.py
boxx/cp.py
boxx/g.py
boxx/gg.py
boxx/p.py
boxx/script.py
boxx/undetermined.py
boxx/ylcompat.py
boxx/yllab.py
boxx/ylsys.py
boxx/ylweb.py
boxx/tool/__init__.py
boxx/tool/toolFunction.py
boxx/tool/toolGui.py
boxx/tool/toolIo.py
boxx/tool/toolLog.py
boxx/tool/toolMarkdown.py
boxx/tool/toolStructObj.py
boxx/tool/toolSystem.py
boxx/tool/toolTools.py
boxx/yldb/__init__.py
boxx/yldb/dbPublicFuncation.py
boxx/yldb/yldf.py
boxx/yldb/ylmysql.py
boxx/yldb/ylsqlite.py
boxx/ylimg/__init__.py
boxx/ylimg/showImgsInBrowser.py
boxx/ylimg/ylimgTool.py
boxx/ylimg/ylimgVideoAndGif.py
boxx/ylml/__init__.py
boxx/ylml/ylDete.py
boxx/ylml/ylmlEvalu.py
boxx/ylml/ylmlTest.py
boxx/ylml/ylmlTrain.py
boxx/ylsci/__init__.py
boxx/ylsci/ylnp.py
boxx/ylsci/ylstatistics.py
boxx/ylsci/ylvector.py
boxx/ylth/__init__.py
boxx/ylth/pthnan.py
boxx-0.10.16.dist-info/METADATA
boxx-0.10.16.dist-info/WHEEL
boxx-0.10.16.dist-info/top_level.txt
boxx-0.10.16.dist-info/RECORD
