Metadata-Version: 2.4
Name: boxx
Version: 0.10.16
Summary: Tool-box for efficient build and debug in Python. Especially for Scientific Computing and Computer Vision.
Home-page: https://github.com/DIYer22/boxx
Download-URL: https://github.com/DIYer22/boxx
Author: DIYer22
Author-email: ylxx@live.com
Maintainer: DIYer22
Maintainer-email: ylxx@live.com
License: MIT
Platform: Windows
Platform: MacOS
Platform: Unix
Classifier: Development Status :: 4 - Beta
Classifier: Intended Audience :: Developers
Classifier: License :: OSI Approved :: MIT License
Classifier: Natural Language :: English
Classifier: Operating System :: Microsoft :: Windows
Classifier: Operating System :: MacOS
Classifier: Operating System :: Unix
Classifier: Programming Language :: Python
Classifier: Programming Language :: Python :: 2.7
Classifier: Programming Language :: Python :: 3.4
Classifier: Programming Language :: Python :: 3.5
Classifier: Programming Language :: Python :: 3.6
Requires-Dist: numpy
Requires-Dist: scikit_image
Requires-Dist: matplotlib
Requires-Dist: pandas
Requires-Dist: imageio
Requires-Dist: snakeviz
Requires-Dist: pyopengl
Requires-Dist: seaborn
Dynamic: author
Dynamic: author-email
Dynamic: classifier
Dynamic: description
Dynamic: download-url
Dynamic: home-page
Dynamic: license
Dynamic: maintainer
Dynamic: maintainer-email
Dynamic: platform
Dynamic: requires-dist
Dynamic: summary
